mlx/.gitignore
mlx/api/model_registry/__init__.py
mlx/api/model_registry/api_client.py
mlx/api/model_registry/api_response.py
mlx/api/model_registry/configuration.py
mlx/api/model_registry/exceptions.py
mlx/api/model_registry/rest.py
mlx/api/model_registry/api/__init__.py
mlx/api/model_registry/api/files_api.py
mlx/api/model_registry/api/health_api.py
mlx/api/model_registry/api/models_api.py
mlx/api/model_registry/api/private_api.py
mlx/api/model_registry/api/public_api.py
mlx/api/model_registry/api/versions_api.py
mlx/api/model_registry/docs/Environment.md
mlx/api/model_registry/docs/ErrorResponse.md
mlx/api/model_registry/docs/File.md
mlx/api/model_registry/docs/FileUploadResponse.md
mlx/api/model_registry/docs/FilesApi.md
mlx/api/model_registry/docs/FilesResponse.md
mlx/api/model_registry/docs/HealthApi.md
mlx/api/model_registry/docs/HealthResponse.md
mlx/api/model_registry/docs/InitUploadResponse.md
mlx/api/model_registry/docs/Model.md
mlx/api/model_registry/docs/ModelRequest.md
mlx/api/model_registry/docs/ModelStorage.md
mlx/api/model_registry/docs/ModelUpdateRequest.md
mlx/api/model_registry/docs/ModelsApi.md
mlx/api/model_registry/docs/ModelsResponse.md
mlx/api/model_registry/docs/PartInfo.md
mlx/api/model_registry/docs/PrivateApi.md
mlx/api/model_registry/docs/PublicApi.md
mlx/api/model_registry/docs/Source.md
mlx/api/model_registry/docs/Training.md
mlx/api/model_registry/docs/UploadCompleteInfo.md
mlx/api/model_registry/docs/Version.md
mlx/api/model_registry/docs/VersionListRequest.md
mlx/api/model_registry/docs/VersionRequest.md
mlx/api/model_registry/docs/VersionStorage.md
mlx/api/model_registry/docs/VersionUpdateRequest.md
mlx/api/model_registry/docs/VersionsApi.md
mlx/api/model_registry/docs/VersionsResponse.md
mlx/api/model_registry/models/__init__.py
mlx/api/model_registry/models/environment.py
mlx/api/model_registry/models/error_response.py
mlx/api/model_registry/models/file.py
mlx/api/model_registry/models/file_upload_response.py
ncloud_mlx_model_registry-0.1.0.dist-info/METADATA
ncloud_mlx_model_registry-0.1.0.dist-info/WHEEL
ncloud_mlx_model_registry-0.1.0.dist-info/entry_points.txt
ncloud_mlx_model_registry-0.1.0.dist-info/licenses/LICENSE
ncloud_mlx_model_registry-0.1.0.dist-info/licenses/NOTICE
ncloud_mlx_model_registry-0.1.0.dist-info/RECORD
