Metadata-Version: 2.4
Name: ncloud-mlx-model-registry
Version: 0.1.0
Summary: CLI and SDK for the ML expert Platform Model Registry on NAVER Cloud Platform
Project-URL: Homepage, https://guide.ncloud-docs.com/docs/ai-mlxp-pmodelregistry
Project-URL: Documentation, https://guide.ncloud-docs.com/docs/ai-mlxp-pmodelregistry
Author-email: navercloud-mlxp <dl_mlx_ncp_dev@navercorp.com>
License-Expression: Apache-2.0
License-File: LICENSE
License-File: NOTICE
Requires-Python: <4.0.0,>=3.9.0
Requires-Dist: aiofiles<24,>=23.2.1
Requires-Dist: httpx<0.28,>=0.27.0
Requires-Dist: ncloud-mlx-sdk>=0.1.1
Requires-Dist: pydantic<3,>=2.7.4
Requires-Dist: python-dateutil<3,>=2.9.0.post0
Requires-Dist: pyyaml<7,>=6.0.1
Requires-Dist: requests<3,>=2.32.3
Requires-Dist: six<2,>=1.16.0
Requires-Dist: tabulate<0.10,>=0.9.0
Requires-Dist: timeago<2,>=1.0.16
Requires-Dist: typer==0.15.4
Requires-Dist: typing==3.7.4.3
Requires-Dist: urllib3[socks]<1.27,>=1.25.4; python_version < '3.10'
Requires-Dist: urllib3[socks]<3,>=2.2.1; python_version >= '3.10'
